scc/RELEASE-VERSION
scc/__init__.py
scc/deploy.py
scc/git.py
scc/main.py
scc/version.py
scc-0.20.0.dist-info/LICENSE.txt
scc-0.20.0.dist-info/METADATA
scc-0.20.0.dist-info/WHEEL
scc-0.20.0.dist-info/entry_points.txt
scc-0.20.0.dist-info/top_level.txt
scc-0.20.0.dist-info/zip-safe
scc-0.20.0.dist-info/RECORD
