Metadata-Version: 2.1
Name: scc
Version: 0.20.0
Summary: OME tools for managing the git(hub) workflow
Home-page: https://github.com/ome/scc
Author: The Open Microscopy Team
Author-email: ome-devel@lists.openmicroscopy.org.uk
License: GPLv2
Platform: UNKNOWN
Classifier: Development Status :: 4 - Beta
Classifier: Environment :: Console
Classifier: Intended Audience :: Developers
Classifier: License :: OSI Approved :: GNU General Public License v2 (GPLv2)
Classifier: Operating System :: OS Independent
Classifier: Programming Language :: Python
Classifier: Topic :: Software Development :: Version Control
Requires-Python: >=3.5
License-File: LICENSE.txt
Requires-Dist: PyGithub (>=1.54)
Requires-Dist: PyYAML (>=5.1)
Requires-Dist: future
Requires-Dist: ruamel.yaml
Requires-Dist: ruamel.yaml.jinja2
Requires-Dist: six
Requires-Dist: urllib3 (<2)
Requires-Dist: yaclifw (<0.3,>=0.2.0)
